drf_emails/__about__.py
drf_emails/__init__.py
drf_emails/apps.py
drf_emails/checks.py
drf_emails/email.py
drf_emails/settings.py
drf_emails/tests.py
drf_emails/typing.py
drf_emails/utils.py
drf_emails/locale/ru/LC_MESSAGES/django.mo
drf_emails/templates/user/email_change_new_confirm_email.html
drf_emails/templates/user/email_change_new_confirm_email.txt
drf_emails/templates/user/email_change_new_confirm_email_subject.txt
drf_emails/templates/user/email_change_old_notify_email.html
drf_emails/templates/user/email_change_old_notify_email.txt
drf_emails/templates/user/email_change_old_notify_email_subject.txt
drf_emails/templates/user/password_reset_email.html
drf_emails/templates/user/password_reset_email.txt
drf_emails/templates/user/password_reset_email_subject.txt
drf_emails/templates/user/signup_email.html
drf_emails/templates/user/signup_email.txt
drf_emails/templates/user/signup_email_subject.txt
drf_emails/templates/user/welcome_email.html
drf_emails/templates/user/welcome_email.txt
drf_emails/templates/user/welcome_email_subject.txt
drf_emails/user/__init__.py
drf_emails/user/abstracts.py
drf_emails/user/apps.py
drf_emails/user/checks.py
drf_emails/user/email.py
drf_emails/user/emails.py
drf_emails/user/managers.py
drf_emails/user/models.py
drf_emails/user/serializers.py
drf_emails/user/tests.py
drf_emails/user/typing.py
drf_emails/user/urls.py
drf_emails/user/views.py
drf_emails/user/migrations/0001_initial.py
drf_emails/user/migrations/__init__.py
drf_emails-0.0.2.dist-info/METADATA
drf_emails-0.0.2.dist-info/WHEEL
drf_emails-0.0.2.dist-info/licenses/LICENSE.txt
drf_emails-0.0.2.dist-info/RECORD
